{
  "replicasUuidToPrincipalId": {
    "fb657df6-882c-4d7e-bafa-fccbcca15bf6": 3,
    "494ff6cb-baa3-41c7-b03f-1da472dd0bc2": 0,
    "0d050f38-d6bf-4f1f-a981-2c07d0ed9903": 2,
    "5eb6693e-8fac-49b4-8927-2fa16682fa4e": 1
  },
  "clientsUuidToPrincipalIds": {
    "e9363262-d99c-4f47-9a3b-f9834f560625": [
      128,
      129,
      130,
      131,
      132,
      133,
      134,
      135,
      136,
      137,
      138,
      139,
      140,
      141,
      142
    ],
    "ad2b9204-dd89-4b05-ba49-20e0ffba1212": [
      8,
      9,
      10,
      11,
      12,
      13,
      14,
      15,
      16,
      17,
      18,
      19,
      20,
      21,
      22
    ],
    "c30eb9e7-75f3-4973-a78d-9013b2730638": [
      98,
      99,
      100,
      101,
      102,
      103,
      104,
      105,
      106,
      107,
      108,
      109,
      110,
      111,
      112
    ],
    "2fc8ba6e-3f14-44e6-b032-432022e9d2c8": [
      38,
      39,
      40,
      41,
      42,
      43,
      44,
      45,
      46,
      47,
      48,
      49,
      50,
      51,
      52
    ],
    "f260abee-53f0-4d28-9ac5-39099e9609b5": [
      53,
      54,
      55,
      56,
      57,
      58,
      59,
      60,
      61,
      62,
      63,
      64,
      65,
      66,
      67
    ],
    "05c3542a-781e-435a-9115-c643d172af75": [
      83,
      84,
      85,
      86,
      87,
      88,
      89,
      90,
      91,
      92,
      93,
      94,
      95,
      96,
      97
    ],
    "160a5adf-9df9-4986-9eaa-633538d2b99f": [
      113,
      114,
      115,
      116,
      117,
      118,
      119,
      120,
      121,
      122,
      123,
      124,
      125,
      126,
      127
    ],
    "5ef3f080-b235-49f4-98d0-88b5e402fe31": [
      68,
      69,
      70,
      71,
      72,
      73,
      74,
      75,
      76,
      77,
      78,
      79,
      80,
      81,
      82
    ],
    "5f3fdf96-7c10-45c3-9476-0ea9b118599d": [
      173,
      174,
      175,
      176,
      177,
      178,
      179,
      180,
      181,
      182,
      183,
      184,
      185,
      186,
      187
    ],
    "1ae0dc8d-51d2-48fb-979d-8915f4604897": [
      23,
      24,
      25,
      26,
      27,
      28,
      29,
      30,
      31,
      32,
      33,
      34,
      35,
      36,
      37
    ],
    "8ed0aa26-d54b-4a58-bc4f-80f008faa77a": [
      143,
      144,
      145,
      146,
      147,
      148,
      149,
      150,
      151,
      152,
      153,
      154,
      155,
      156,
      157
    ],
    "824ea7a3-f300-44c4-a67e-f766f92a8059": [
      158,
      159,
      160,
      161,
      162,
      163,
      164,
      165,
      166,
      167,
      168,
      169,
      170,
      171,
      172
    ]
  }
}